syize/__init__.py
syize/diff.py
syize/diff_run.py
syize/picture.py
syize/picture_run.py
syize/plot.py
syize/string.py
syize/string_run.py
syize/utils.py
syize-1.2.6.dist-info/METADATA
syize-1.2.6.dist-info/WHEEL
syize-1.2.6.dist-info/entry_points.txt
syize-1.2.6.dist-info/top_level.txt
syize-1.2.6.dist-info/RECORD
